{
  "uploads": [
    {
      "timestamp": "2026-01-01T14:56:01.293293",
      "model_id": "model_20260101_145556",
      "samples": 10000
    },
    {
      "timestamp": "2026-01-01T15:10:42.014424",
      "model_id": "model_20260101_151036",
      "samples": 10000
    },
    {
      "timestamp": "2026-01-01T15:17:54.514243",
      "model_id": "model_20260101_151749",
      "samples": 10000
    },
    {
      "timestamp": "2026-01-01T15:20:20.421498",
      "model_id": "model_20260101_152015",
      "samples": 10000
    },
    {
      "timestamp": "2026-01-01T15:26:35.187040",
      "model_id": "model_20260101_152630",
      "samples": 10000
    },
    {
      "timestamp": "2026-01-01T15:28:13.862695",
      "model_id": "model_20260101_152808",
      "samples": 10000
    },
    {
      "timestamp": "2026-01-01T15:30:58.264456",
      "model_id": "model_20260101_153053",
      "samples": 10000
    },
    {
      "timestamp": "2026-01-01T16:29:14.725116",
      "model_id": "model_20260101_162908",
      "samples": 10000
    }
  ],
  "predictions": [
    {
      "timestamp": "2026-01-01T15:43:54.887755",
      "model_id": "model_20260101_153053",
      "avg_trust_score": 78.75453600000037,
      "total_predictions": 10000
    }
  ]
}